wotoplatform/__init__.py
wotoplatform/tools.py
wotoplatform/types/__init__.py
wotoplatform/types/base_types/scaffold.py
wotoplatform/types/clientBase.py
wotoplatform/types/data_types/__init__.py
wotoplatform/types/data_types/groups_data.py
wotoplatform/types/data_types/users_data.py
wotoplatform/types/data_types/version_data.py
wotoplatform/types/errors/__init__.py
wotoplatform/types/errors/client_errors.py
wotoplatform/types/errors/general.py
wotoplatform/types/errors/parser.py
wotoplatform/types/errors/server_errors.py
wotoplatform/types/permissions.py
wotoplatform/utils/__init__.py
wotoplatform/utils/woto_crypto/__init__.py
wotoplatform/utils/woto_crypto/common.py
wotoplatform/utils/woto_crypto/password_container.py
wotoplatform/utils/woto_socket.py
wotoplatform-0.0.25.dist-info/LICENSE
wotoplatform-0.0.25.dist-info/WHEEL
wotoplatform-0.0.25.dist-info/METADATA
wotoplatform-0.0.25.dist-info/RECORD
